automationscript/__init__.py
automationscript/automationscript.py
dreamteam-0.0.1.dist-info/LICENSE
dreamteam-0.0.1.dist-info/METADATA
dreamteam-0.0.1.dist-info/WHEEL
dreamteam-0.0.1.dist-info/top_level.txt
dreamteam-0.0.1.dist-info/RECORD
