Metadata-Version: 2.1
Name: dreamteam
Version: 0.0.1
Summary: Automated package
Home-page: https://github.com/moezali1/
Author: Dream-Team
Author-email: abhinav.arora@queensu.ca
License: UNKNOWN
Platform: UNKNOWN
Classifier: Programming Language :: Python :: 3
Classifier: License :: OSI Approved :: MIT License
Classifier: Operating System :: OS Independent
Requires-Python: >=3.6
